{"resourceType":"CodeSystem","id":"building-type-code","meta":{"versionId":"1","lastUpdated":"2024-10-29T17:14:59.703+13:00"},"url":"https://standards.digital.health.nz/ns/building-type-code","version":"1.0","name":"building_type_code","title":"Building type code","status":"active","experimental":false,"date":"2024-09-10","publisher":"New Zealand Health Terminology Service","contact":[{"name":"NZHTS Support","telecom":[{"system":"email","value":"standards@tewhatuora.govt.nz"}]}],"description":"buiilding type code","content":"complete","concept":[{"code":"1","display":"Residential buildings"},{"code":"11","display":"Dwelling units","property":[{"code":"parent","valueCode":"1"}]},{"code":"111","display":"Houses","property":[{"code":"parent","valueCode":"11"}]},{"code":"1111","display":"Houses","designation":[{"language":"en-NZ","use":{"system":"http://snomed.info/sct","code":"900000000000013009"},"value":"Bach"},{"language":"en-NZ","use":{"system":"http://snomed.info/sct","code":"900000000000013009"},"value":"Crib"},{"language":"en-NZ","use":{"system":"http://snomed.info/sct","code":"900000000000013009"},"value":"House"},{"language":"en-NZ","use":{"system":"http://snomed.info/sct","code":"900000000000013009"},"value":"Chalet domestic"},{"language":"en-NZ","use":{"system":"http://snomed.info/sct","code":"900000000000013009"},"value":"Dwelling"},{"language":"en-NZ","use":{"system":"http://snomed.info/sct","code":"900000000000013009"},"value":"Manse"},{"language":"en-NZ","use":{"system":"http://snomed.info/sct","code":"900000000000013009"},"value":"New dwelling"},{"language":"en-NZ","use":{"system":"http://snomed.info/sct","code":"900000000000013009"},"value":"New house"},{"language":"en-NZ","use":{"system":"http://snomed.info/sct","code":"900000000000013009"},"value":"Vergola"}],"property":[{"code":"parent","valueCode":"111"}]},{"code":"112","display":"Apartments, townhouses, units, and other dwellings","property":[{"code":"parent","valueCode":"11"}]},{"code":"1121","display":"Apartments","designation":[{"language":"en-NZ","use":{"system":"http://snomed.info/sct","code":"900000000000013009"},"value":"Apartment"},{"language":"en-NZ","use":{"system":"http://snomed.info/sct","code":"900000000000013009"},"value":"Apartments"}],"property":[{"code":"parent","valueCode":"112"}]},{"code":"1122","display":"Retirement village units","designation":[{"language":"en-NZ","use":{"system":"http://snomed.info/sct","code":"900000000000013009"},"value":"Retirement"},{"language":"en-NZ","use":{"system":"http://snomed.info/sct","code":"900000000000013009"},"value":"Retirement units"}],"property":[{"code":"parent","valueCode":"112"}]},{"code":"1129","display":"Townhouses, flats, units, and other dwellings","designation":[{"language":"en-NZ","use":{"system":"http://snomed.info/sct","code":"900000000000013009"},"value":"Flat"},{"language":"en-NZ","use":{"system":"http://snomed.info/sct","code":"900000000000013009"},"value":"Granny flat"},{"language":"en-NZ","use":{"system":"http://snomed.info/sct","code":"900000000000013009"},"value":"Unit"},{"language":"en-NZ","use":{"system":"http://snomed.info/sct","code":"900000000000013009"},"value":"Townhouse"},{"language":"en-NZ","use":{"system":"http://snomed.info/sct","code":"900000000000013009"},"value":"Flat added to dwelling"},{"language":"en-NZ","use":{"system":"http://snomed.info/sct","code":"900000000000013009"},"value":"Flat added to other building"},{"language":"en-NZ","use":{"system":"http://snomed.info/sct","code":"900000000000013009"},"value":"Other residential buildings"},{"language":"en-NZ","use":{"system":"http://snomed.info/sct","code":"900000000000013009"},"value":"Studio"},{"language":"en-NZ","use":{"system":"http://snomed.info/sct","code":"900000000000013009"},"value":"Unit domestic"},{"language":"en-NZ","use":{"system":"http://snomed.info/sct","code":"900000000000013009"},"value":"Unit/flat/townhouse/studio"},{"language":"en-NZ","use":{"system":"http://snomed.info/sct","code":"900000000000013009"},"value":"Villa duplexes"}],"property":[{"code":"parent","valueCode":"112"}]},{"code":"12","display":"Domestic outbuildings","property":[{"code":"parent","valueCode":"1"}]},{"code":"121","display":"Domestic outbuildings","property":[{"code":"parent","valueCode":"12"}]},{"code":"1211","display":"Domestic outbuildings","designation":[{"language":"en-NZ","use":{"system":"http://snomed.info/sct","code":"900000000000013009"},"value":"Garage"},{"language":"en-NZ","use":{"system":"http://snomed.info/sct","code":"900000000000013009"},"value":"Sleepout"},{"language":"en-NZ","use":{"system":"http://snomed.info/sct","code":"900000000000013009"},"value":"Garden shed"},{"language":"en-NZ","use":{"system":"http://snomed.info/sct","code":"900000000000013009"},"value":"Boatshed"},{"language":"en-NZ","use":{"system":"http://snomed.info/sct","code":"900000000000013009"},"value":"Car deck domestic"},{"language":"en-NZ","use":{"system":"http://snomed.info/sct","code":"900000000000013009"},"value":"Carport"},{"language":"en-NZ","use":{"system":"http://snomed.info/sct","code":"900000000000013009"},"value":"Domestic outbuildings"},{"language":"en-NZ","use":{"system":"http://snomed.info/sct","code":"900000000000013009"},"value":"Games room"},{"language":"en-NZ","use":{"system":"http://snomed.info/sct","code":"900000000000013009"},"value":"Gazebo"},{"language":"en-NZ","use":{"system":"http://snomed.info/sct","code":"900000000000013009"},"value":"Glass house domestic"},{"language":"en-NZ","use":{"system":"http://snomed.info/sct","code":"900000000000013009"},"value":"Hen house domestic"},{"language":"en-NZ","use":{"system":"http://snomed.info/sct","code":"900000000000013009"},"value":"Outbuilding"},{"language":"en-NZ","use":{"system":"http://snomed.info/sct","code":"900000000000013009"},"value":"Outhouse"},{"language":"en-NZ","use":{"system":"http://snomed.info/sct","code":"900000000000013009"},"value":"Pagoda"},{"language":"en-NZ","use":{"system":"http://snomed.info/sct","code":"900000000000013009"},"value":"Play house domestic"},{"language":"en-NZ","use":{"system":"http://snomed.info/sct","code":"900000000000013009"},"value":"Pool house domestic"},{"language":"en-NZ","use":{"system":"http://snomed.info/sct","code":"900000000000013009"},"value":"Shed domestic"},{"language":"en-NZ","use":{"system":"http://snomed.info/sct","code":"900000000000013009"},"value":"Studio residential"},{"language":"en-NZ","use":{"system":"http://snomed.info/sct","code":"900000000000013009"},"value":"Summer house"},{"language":"en-NZ","use":{"system":"http://snomed.info/sct","code":"900000000000013009"},"value":"Toolshed domestic"},{"language":"en-NZ","use":{"system":"http://snomed.info/sct","code":"900000000000013009"},"value":"Workshop domestic"}],"property":[{"code":"parent","valueCode":"121"}]},{"code":"2","display":"Non-residential buildings"},{"code":"21","display":"Hotels, motels, boarding houses, and prisons","property":[{"code":"parent","valueCode":"2"}]},{"code":"211","display":"Hostels, boarding houses, and prisons","property":[{"code":"parent","valueCode":"21"}]},{"code":"2111","display":"Prisons","designation":[{"language":"en-NZ","use":{"system":"http://snomed.info/sct","code":"900000000000013009"},"value":"Prison"},{"language":"en-NZ","use":{"system":"http://snomed.info/sct","code":"900000000000013009"},"value":"Prisons"},{"language":"en-NZ","use":{"system":"http://snomed.info/sct","code":"900000000000013009"},"value":"Correctional"},{"language":"en-NZ","use":{"system":"http://snomed.info/sct","code":"900000000000013009"},"value":"Residential youth centre"}],"property":[{"code":"parent","valueCode":"211"}]},{"code":"2119","display":"Hostels, boarding houses, and other long-term accommodation","designation":[{"language":"en-NZ","use":{"system":"http://snomed.info/sct","code":"900000000000013009"},"value":"Barracks"},{"language":"en-NZ","use":{"system":"http://snomed.info/sct","code":"900000000000013009"},"value":"Boarding house"},{"language":"en-NZ","use":{"system":"http://snomed.info/sct","code":"900000000000013009"},"value":"Convent"},{"language":"en-NZ","use":{"system":"http://snomed.info/sct","code":"900000000000013009"},"value":"Hostel"},{"language":"en-NZ","use":{"system":"http://snomed.info/sct","code":"900000000000013009"},"value":"Nurses home"},{"language":"en-NZ","use":{"system":"http://snomed.info/sct","code":"900000000000013009"},"value":"Orphanage"},{"language":"en-NZ","use":{"system":"http://snomed.info/sct","code":"900000000000013009"},"value":"Shearers quarters"},{"language":"en-NZ","use":{"system":"http://snomed.info/sct","code":"900000000000013009"},"value":"Communal accommodation"},{"language":"en-NZ","use":{"system":"http://snomed.info/sct","code":"900000000000013009"},"value":"Workers quarters"},{"language":"en-NZ","use":{"system":"http://snomed.info/sct","code":"900000000000013009"},"value":"School hostel"},{"language":"en-NZ","use":{"system":"http://snomed.info/sct","code":"900000000000013009"},"value":"Childrens home"},{"language":"en-NZ","use":{"system":"http://snomed.info/sct","code":"900000000000013009"},"value":"Children's home"},{"language":"en-NZ","use":{"system":"http://snomed.info/sct","code":"900000000000013009"},"value":"Community care"},{"language":"en-NZ","use":{"system":"http://snomed.info/sct","code":"900000000000013009"},"value":"Dormitory school"},{"language":"en-NZ","use":{"system":"http://snomed.info/sct","code":"900000000000013009"},"value":"Farm workers accommodation"},{"language":"en-NZ","use":{"system":"http://snomed.info/sct","code":"900000000000013009"},"value":"IHC residential care"},{"language":"en-NZ","use":{"system":"http://snomed.info/sct","code":"900000000000013009"},"value":"Nurse hostel"},{"language":"en-NZ","use":{"system":"http://snomed.info/sct","code":"900000000000013009"},"value":"Rehabilitation Accom"},{"language":"en-NZ","use":{"system":"http://snomed.info/sct","code":"900000000000013009"},"value":"Ronald mcdonald House"},{"language":"en-NZ","use":{"system":"http://snomed.info/sct","code":"900000000000013009"},"value":"Single mens quarters"},{"language":"en-NZ","use":{"system":"http://snomed.info/sct","code":"900000000000013009"},"value":"Students apartments"},{"language":"en-NZ","use":{"system":"http://snomed.info/sct","code":"900000000000013009"},"value":"University hostel"},{"language":"en-NZ","use":{"system":"http://snomed.info/sct","code":"900000000000013009"},"value":"Hostels boarding houses and other long-term accommodation"}],"property":[{"code":"parent","valueCode":"211"}]},{"code":"212","display":"Hotels, motels, and other short-term accommodation","property":[{"code":"parent","valueCode":"21"}]},{"code":"2121","display":"Hotels, motels, and other short-term accommodation","designation":[{"language":"en-NZ","use":{"system":"http://snomed.info/sct","code":"900000000000013009"},"value":"Home stay"},{"language":"en-NZ","use":{"system":"http://snomed.info/sct","code":"900000000000013009"},"value":"Hotel"},{"language":"en-NZ","use":{"system":"http://snomed.info/sct","code":"900000000000013009"},"value":"Motel"},{"language":"en-NZ","use":{"system":"http://snomed.info/sct","code":"900000000000013009"},"value":"Motor camp"},{"language":"en-NZ","use":{"system":"http://snomed.info/sct","code":"900000000000013009"},"value":"Trampers hut"},{"language":"en-NZ","use":{"system":"http://snomed.info/sct","code":"900000000000013009"},"value":"Youth hostel"},{"language":"en-NZ","use":{"system":"http://snomed.info/sct","code":"900000000000013009"},"value":"Guest house"},{"language":"en-NZ","use":{"system":"http://snomed.info/sct","code":"900000000000013009"},"value":"Timeshare unit"},{"language":"en-NZ","use":{"system":"http://snomed.info/sct","code":"900000000000013009"},"value":"Farm stay"},{"language":"en-NZ","use":{"system":"http://snomed.info/sct","code":"900000000000013009"},"value":"Motor lodge"},{"language":"en-NZ","use":{"system":"http://snomed.info/sct","code":"900000000000013009"},"value":"Back packer"},{"language":"en-NZ","use":{"system":"http://snomed.info/sct","code":"900000000000013009"},"value":"Backpacker"},{"language":"en-NZ","use":{"system":"http://snomed.info/sct","code":"900000000000013009"},"value":"Cabins motor camp"},{"language":"en-NZ","use":{"system":"http://snomed.info/sct","code":"900000000000013009"},"value":"Chalet motel"},{"language":"en-NZ","use":{"system":"http://snomed.info/sct","code":"900000000000013009"},"value":"Chalet motor camp"},{"language":"en-NZ","use":{"system":"http://snomed.info/sct","code":"900000000000013009"},"value":"Conservation Huts"},{"language":"en-NZ","use":{"system":"http://snomed.info/sct","code":"900000000000013009"},"value":"Holiday park cabins"},{"language":"en-NZ","use":{"system":"http://snomed.info/sct","code":"900000000000013009"},"value":"Hostel backpackers"},{"language":"en-NZ","use":{"system":"http://snomed.info/sct","code":"900000000000013009"},"value":"Hotels motels and other short-term accommodation"},{"language":"en-NZ","use":{"system":"http://snomed.info/sct","code":"900000000000013009"},"value":"School camps"}],"property":[{"code":"parent","valueCode":"212"}]},{"code":"22","display":"Hospitals, nursing homes, and other health buildings","property":[{"code":"parent","valueCode":"2"}]},{"code":"221","display":"Hospitals, nursing homes, and other health buildings","property":[{"code":"parent","valueCode":"22"}]},{"code":"2211","display":"Hospitals","designation":[{"language":"en-NZ","use":{"system":"http://snomed.info/sct","code":"900000000000013009"},"value":"Hospitals"},{"language":"en-NZ","use":{"system":"http://snomed.info/sct","code":"900000000000013009"},"value":"Hospital"},{"language":"en-NZ","use":{"system":"http://snomed.info/sct","code":"900000000000013009"},"value":"Boiler house hospital"},{"language":"en-NZ","use":{"system":"http://snomed.info/sct","code":"900000000000013009"},"value":"Laboratory hospital"}],"property":[{"code":"parent","valueCode":"221"}]},{"code":"2212","display":"Hospices, rest homes, and retirement villages (excluding units)","designation":[{"language":"en-NZ","use":{"system":"http://snomed.info/sct","code":"900000000000013009"},"value":"Hospice"},{"language":"en-NZ","use":{"system":"http://snomed.info/sct","code":"900000000000013009"},"value":"Rest home"},{"language":"en-NZ","use":{"system":"http://snomed.info/sct","code":"900000000000013009"},"value":"Retirement village"},{"language":"en-NZ","use":{"system":"http://snomed.info/sct","code":"900000000000013009"},"value":"Convalescence"},{"language":"en-NZ","use":{"system":"http://snomed.info/sct","code":"900000000000013009"},"value":"Old peoples home"},{"language":"en-NZ","use":{"system":"http://snomed.info/sct","code":"900000000000013009"},"value":"Hospice rest homes and retirement villages (excl. Units)"},{"language":"en-NZ","use":{"system":"http://snomed.info/sct","code":"900000000000013009"},"value":"Convalesence"},{"language":"en-NZ","use":{"system":"http://snomed.info/sct","code":"900000000000013009"},"value":"Elderly peoples home"},{"language":"en-NZ","use":{"system":"http://snomed.info/sct","code":"900000000000013009"},"value":"Geriatric home"},{"language":"en-NZ","use":{"system":"http://snomed.info/sct","code":"900000000000013009"},"value":"Nursing home"}],"property":[{"code":"parent","valueCode":"221"}]},{"code":"2219","display":"Other health buildings","designation":[{"language":"en-NZ","use":{"system":"http://snomed.info/sct","code":"900000000000013009"},"value":"Dentist"},{"language":"en-NZ","use":{"system":"http://snomed.info/sct","code":"900000000000013009"},"value":"Health camp"},{"language":"en-NZ","use":{"system":"http://snomed.info/sct","code":"900000000000013009"},"value":"Counselling"},{"language":"en-NZ","use":{"system":"http://snomed.info/sct","code":"900000000000013009"},"value":"Surgery"},{"language":"en-NZ","use":{"system":"http://snomed.info/sct","code":"900000000000013009"},"value":"Other health buildings"},{"language":"en-NZ","use":{"system":"http://snomed.info/sct","code":"900000000000013009"},"value":"Medical laboratory"},{"language":"en-NZ","use":{"system":"http://snomed.info/sct","code":"900000000000013009"},"value":"Medical centre"},{"language":"en-NZ","use":{"system":"http://snomed.info/sct","code":"900000000000013009"},"value":"Childrens health camp"},{"language":"en-NZ","use":{"system":"http://snomed.info/sct","code":"900000000000013009"},"value":"Dental clinic"},{"language":"en-NZ","use":{"system":"http://snomed.info/sct","code":"900000000000013009"},"value":"Consulting room"},{"language":"en-NZ","use":{"system":"http://snomed.info/sct","code":"900000000000013009"},"value":"Doctors room"},{"language":"en-NZ","use":{"system":"http://snomed.info/sct","code":"900000000000013009"},"value":"Health centre"},{"language":"en-NZ","use":{"system":"http://snomed.info/sct","code":"900000000000013009"},"value":"Plunket room"}],"property":[{"code":"parent","valueCode":"221"}]},{"code":"23","display":"Education buildings","property":[{"code":"parent","valueCode":"2"}]},{"code":"231","display":"Education buildings","property":[{"code":"parent","valueCode":"23"}]},{"code":"2311","display":"Pre-school education buildings","designation":[{"language":"en-NZ","use":{"system":"http://snomed.info/sct","code":"900000000000013009"},"value":"Kindergarten"},{"language":"en-NZ","use":{"system":"http://snomed.info/sct","code":"900000000000013009"},"value":"Playcentre"},{"language":"en-NZ","use":{"system":"http://snomed.info/sct","code":"900000000000013009"},"value":"Creche"},{"language":"en-NZ","use":{"system":"http://snomed.info/sct","code":"900000000000013009"},"value":"Preschool"},{"language":"en-NZ","use":{"system":"http://snomed.info/sct","code":"900000000000013009"},"value":"Kohanga reo"},{"language":"en-NZ","use":{"system":"http://snomed.info/sct","code":"900000000000013009"},"value":"Day care"},{"language":"en-NZ","use":{"system":"http://snomed.info/sct","code":"900000000000013009"},"value":"Child care centre"},{"language":"en-NZ","use":{"system":"http://snomed.info/sct","code":"900000000000013009"},"value":"Chipmunks"},{"language":"en-NZ","use":{"system":"http://snomed.info/sct","code":"900000000000013009"},"value":"Kindercare"},{"language":"en-NZ","use":{"system":"http://snomed.info/sct","code":"900000000000013009"},"value":"Kindy"},{"language":"en-NZ","use":{"system":"http://snomed.info/sct","code":"900000000000013009"},"value":"Lollypops"},{"language":"en-NZ","use":{"system":"http://snomed.info/sct","code":"900000000000013009"},"value":"Pre-school education buildings"},{"language":"en-NZ","use":{"system":"http://snomed.info/sct","code":"900000000000013009"},"value":"Te Kohunga Reo"}],"property":[{"code":"parent","valueCode":"231"}]},{"code":"2312","display":"School buildings","designation":[{"language":"en-NZ","use":{"system":"http://snomed.info/sct","code":"900000000000013009"},"value":"Primary school"},{"language":"en-NZ","use":{"system":"http://snomed.info/sct","code":"900000000000013009"},"value":"Secondary school"},{"language":"en-NZ","use":{"system":"http://snomed.info/sct","code":"900000000000013009"},"value":"School"},{"language":"en-NZ","use":{"system":"http://snomed.info/sct","code":"900000000000013009"},"value":"Intermediate school"},{"language":"en-NZ","use":{"system":"http://snomed.info/sct","code":"900000000000013009"},"value":"Area school"},{"language":"en-NZ","use":{"system":"http://snomed.info/sct","code":"900000000000013009"},"value":"Boiler house school"},{"language":"en-NZ","use":{"system":"http://snomed.info/sct","code":"900000000000013009"},"value":"Gymnasium school"},{"language":"en-NZ","use":{"system":"http://snomed.info/sct","code":"900000000000013009"},"value":"Laboratory school"},{"language":"en-NZ","use":{"system":"http://snomed.info/sct","code":"900000000000013009"},"value":"Library school"},{"language":"en-NZ","use":{"system":"http://snomed.info/sct","code":"900000000000013009"},"value":"School buildings"}],"property":[{"code":"parent","valueCode":"231"}]},{"code":"2319","display":"Tertiary and other education buildings","designation":[{"language":"en-NZ","use":{"system":"http://snomed.info/sct","code":"900000000000013009"},"value":"Polytechnic"},{"language":"en-NZ","use":{"system":"http://snomed.info/sct","code":"900000000000013009"},"value":"University"},{"language":"en-NZ","use":{"system":"http://snomed.info/sct","code":"900000000000013009"},"value":"College of Education"},{"language":"en-NZ","use":{"system":"http://snomed.info/sct","code":"900000000000013009"},"value":"Laboratory university"},{"language":"en-NZ","use":{"system":"http://snomed.info/sct","code":"900000000000013009"},"value":"Library university"},{"language":"en-NZ","use":{"system":"http://snomed.info/sct","code":"900000000000013009"},"value":"Teachers college"},{"language":"en-NZ","use":{"system":"http://snomed.info/sct","code":"900000000000013009"},"value":"Technical institute"},{"language":"en-NZ","use":{"system":"http://snomed.info/sct","code":"900000000000013009"},"value":"Tertiary"},{"language":"en-NZ","use":{"system":"http://snomed.info/sct","code":"900000000000013009"},"value":"Tertiary and other education buildings"},{"language":"en-NZ","use":{"system":"http://snomed.info/sct","code":"900000000000013009"},"value":"Training"}],"property":[{"code":"parent","valueCode":"231"}]},{"code":"24","display":"Social, cultural, and religious buildings","property":[{"code":"parent","valueCode":"2"}]},{"code":"241","display":"Social, cultural, and religious buildings","property":[{"code":"parent","valueCode":"24"}]},{"code":"2411","display":"Sports facilities","designation":[{"language":"en-NZ","use":{"system":"http://snomed.info/sct","code":"900000000000013009"},"value":"Fitness centre"},{"language":"en-NZ","use":{"system":"http://snomed.info/sct","code":"900000000000013009"},"value":"Gymnasium"},{"language":"en-NZ","use":{"system":"http://snomed.info/sct","code":"900000000000013009"},"value":"Sports facilities"},{"language":"en-NZ","use":{"system":"http://snomed.info/sct","code":"900000000000013009"},"value":"Squash court"},{"language":"en-NZ","use":{"system":"http://snomed.info/sct","code":"900000000000013009"},"value":"Club racing"},{"language":"en-NZ","use":{"system":"http://snomed.info/sct","code":"900000000000013009"},"value":"Grandstand"},{"language":"en-NZ","use":{"system":"http://snomed.info/sct","code":"900000000000013009"},"value":"Gym"},{"language":"en-NZ","use":{"system":"http://snomed.info/sct","code":"900000000000013009"},"value":"Racing club"},{"language":"en-NZ","use":{"system":"http://snomed.info/sct","code":"900000000000013009"},"value":"Sport facility"},{"language":"en-NZ","use":{"system":"http://snomed.info/sct","code":"900000000000013009"},"value":"Sports facility"},{"language":"en-NZ","use":{"system":"http://snomed.info/sct","code":"900000000000013009"},"value":"Stable racing club"},{"language":"en-NZ","use":{"system":"http://snomed.info/sct","code":"900000000000013009"},"value":"Stadium"}],"property":[{"code":"parent","valueCode":"241"}]},{"code":"2412","display":"Museums, art galleries, and libraries","designation":[{"language":"en-NZ","use":{"system":"http://snomed.info/sct","code":"900000000000013009"},"value":"Library"},{"language":"en-NZ","use":{"system":"http://snomed.info/sct","code":"900000000000013009"},"value":"Art gallery"},{"language":"en-NZ","use":{"system":"http://snomed.info/sct","code":"900000000000013009"},"value":"Museum"},{"language":"en-NZ","use":{"system":"http://snomed.info/sct","code":"900000000000013009"},"value":"Museums art galleries and libraries"}],"property":[{"code":"parent","valueCode":"241"}]},{"code":"2413","display":"Religious buildings","designation":[{"language":"en-NZ","use":{"system":"http://snomed.info/sct","code":"900000000000013009"},"value":"Church"},{"language":"en-NZ","use":{"system":"http://snomed.info/sct","code":"900000000000013009"},"value":"Religious"},{"language":"en-NZ","use":{"system":"http://snomed.info/sct","code":"900000000000013009"},"value":"Religious buildings"},{"language":"en-NZ","use":{"system":"http://snomed.info/sct","code":"900000000000013009"},"value":"Mausoleum"}],"property":[{"code":"parent","valueCode":"241"}]},{"code":"2414","display":"Marae","designation":[{"language":"en-NZ","use":{"system":"http://snomed.info/sct","code":"900000000000013009"},"value":"Marae"}],"property":[{"code":"parent","valueCode":"241"}]},{"code":"2419","display":"Other cultural, social, and entertainment buildings","designation":[{"language":"en-NZ","use":{"system":"http://snomed.info/sct","code":"900000000000013009"},"value":"RSA"},{"language":"en-NZ","use":{"system":"http://snomed.info/sct","code":"900000000000013009"},"value":"Amusement park"},{"language":"en-NZ","use":{"system":"http://snomed.info/sct","code":"900000000000013009"},"value":"Theatre"},{"language":"en-NZ","use":{"system":"http://snomed.info/sct","code":"900000000000013009"},"value":"Clubroom"},{"language":"en-NZ","use":{"system":"http://snomed.info/sct","code":"900000000000013009"},"value":"Community hall"},{"language":"en-NZ","use":{"system":"http://snomed.info/sct","code":"900000000000013009"},"value":"Public toilets"},{"language":"en-NZ","use":{"system":"http://snomed.info/sct","code":"900000000000013009"},"value":"Aquatic centre"},{"language":"en-NZ","use":{"system":"http://snomed.info/sct","code":"900000000000013009"},"value":"Country club"},{"language":"en-NZ","use":{"system":"http://snomed.info/sct","code":"900000000000013009"},"value":"Massage parlour"},{"language":"en-NZ","use":{"system":"http://snomed.info/sct","code":"900000000000013009"},"value":"Night club"},{"language":"en-NZ","use":{"system":"http://snomed.info/sct","code":"900000000000013009"},"value":"Masonic lodge"},{"language":"en-NZ","use":{"system":"http://snomed.info/sct","code":"900000000000013009"},"value":"Agricultural park"},{"language":"en-NZ","use":{"system":"http://snomed.info/sct","code":"900000000000013009"},"value":"Bowling green"},{"language":"en-NZ","use":{"system":"http://snomed.info/sct","code":"900000000000013009"},"value":"Brothel"},{"language":"en-NZ","use":{"system":"http://snomed.info/sct","code":"900000000000013009"},"value":"Casino"},{"language":"en-NZ","use":{"system":"http://snomed.info/sct","code":"900000000000013009"},"value":"Cinema"},{"language":"en-NZ","use":{"system":"http://snomed.info/sct","code":"900000000000013009"},"value":"Club chartered"},{"language":"en-NZ","use":{"system":"http://snomed.info/sct","code":"900000000000013009"},"value":"Club room"},{"language":"en-NZ","use":{"system":"http://snomed.info/sct","code":"900000000000013009"},"value":"Convention centre"},{"language":"en-NZ","use":{"system":"http://snomed.info/sct","code":"900000000000013009"},"value":"Crematorium"},{"language":"en-NZ","use":{"system":"http://snomed.info/sct","code":"900000000000013009"},"value":"Funeral parlour"},{"language":"en-NZ","use":{"system":"http://snomed.info/sct","code":"900000000000013009"},"value":"Hall"},{"language":"en-NZ","use":{"system":"http://snomed.info/sct","code":"900000000000013009"},"value":"Indoor riding arena"},{"language":"en-NZ","use":{"system":"http://snomed.info/sct","code":"900000000000013009"},"value":"Movie theatre"},{"language":"en-NZ","use":{"system":"http://snomed.info/sct","code":"900000000000013009"},"value":"Nightclub"},{"language":"en-NZ","use":{"system":"http://snomed.info/sct","code":"900000000000013009"},"value":"Observatory"},{"language":"en-NZ","use":{"system":"http://snomed.info/sct","code":"900000000000013009"},"value":"Other social cultural and entertainment buildings"},{"language":"en-NZ","use":{"system":"http://snomed.info/sct","code":"900000000000013009"},"value":"Other social cultural entertainment buildings"},{"language":"en-NZ","use":{"system":"http://snomed.info/sct","code":"900000000000013009"},"value":"Picture theatre"},{"language":"en-NZ","use":{"system":"http://snomed.info/sct","code":"900000000000013009"},"value":"Play house theatre"},{"language":"en-NZ","use":{"system":"http://snomed.info/sct","code":"900000000000013009"},"value":"Retreats"},{"language":"en-NZ","use":{"system":"http://snomed.info/sct","code":"900000000000013009"},"value":"Riding for the disabled"},{"language":"en-NZ","use":{"system":"http://snomed.info/sct","code":"900000000000013009"},"value":"Rifle range council"},{"language":"en-NZ","use":{"system":"http://snomed.info/sct","code":"900000000000013009"},"value":"Scout hall"},{"language":"en-NZ","use":{"system":"http://snomed.info/sct","code":"900000000000013009"},"value":"Sergeants mess"},{"language":"en-NZ","use":{"system":"http://snomed.info/sct","code":"900000000000013009"},"value":"Show grounds"},{"language":"en-NZ","use":{"system":"http://snomed.info/sct","code":"900000000000013009"},"value":"Skating rink"},{"language":"en-NZ","use":{"system":"http://snomed.info/sct","code":"900000000000013009"},"value":"Theatre performing arts"},{"language":"en-NZ","use":{"system":"http://snomed.info/sct","code":"900000000000013009"},"value":"Visitors centre"},{"language":"en-NZ","use":{"system":"http://snomed.info/sct","code":"900000000000013009"},"value":"Working mens club"},{"language":"en-NZ","use":{"system":"http://snomed.info/sct","code":"900000000000013009"},"value":"Zoo buildings"}],"property":[{"code":"parent","valueCode":"241"}]},{"code":"25","display":"Commercial buildings","property":[{"code":"parent","valueCode":"2"}]},{"code":"251","display":"Shops, restaurants, and bars","property":[{"code":"parent","valueCode":"25"}]},{"code":"2511","display":"Supermarkets","designation":[{"language":"en-NZ","use":{"system":"http://snomed.info/sct","code":"900000000000013009"},"value":"Supermarket"}],"property":[{"code":"parent","valueCode":"251"}]},{"code":"2512","display":"Restaurants, bars, and cafes","designation":[{"language":"en-NZ","use":{"system":"http://snomed.info/sct","code":"900000000000013009"},"value":"KFC"},{"language":"en-NZ","use":{"system":"http://snomed.info/sct","code":"900000000000013009"},"value":"Cafe"},{"language":"en-NZ","use":{"system":"http://snomed.info/sct","code":"900000000000013009"},"value":"Restaurant"},{"language":"en-NZ","use":{"system":"http://snomed.info/sct","code":"900000000000013009"},"value":"Subway"},{"language":"en-NZ","use":{"system":"http://snomed.info/sct","code":"900000000000013009"},"value":"Bar"},{"language":"en-NZ","use":{"system":"http://snomed.info/sct","code":"900000000000013009"},"value":"Tavern"},{"language":"en-NZ","use":{"system":"http://snomed.info/sct","code":"900000000000013009"},"value":"Cafeteria"},{"language":"en-NZ","use":{"system":"http://snomed.info/sct","code":"900000000000013009"},"value":"Coffee bar"},{"language":"en-NZ","use":{"system":"http://snomed.info/sct","code":"900000000000013009"},"value":"Hotel bar"},{"language":"en-NZ","use":{"system":"http://snomed.info/sct","code":"900000000000013009"},"value":"Mcdonalds"},{"language":"en-NZ","use":{"system":"http://snomed.info/sct","code":"900000000000013009"},"value":"Restaurants bars and cafes"},{"language":"en-NZ","use":{"system":"http://snomed.info/sct","code":"900000000000013009"},"value":"Wine bar"}],"property":[{"code":"parent","valueCode":"251"}]},{"code":"2519","display":"Other shops and retail buildings","designation":[{"language":"en-NZ","use":{"system":"http://snomed.info/sct","code":"900000000000013009"},"value":"Hairdresser"},{"language":"en-NZ","use":{"system":"http://snomed.info/sct","code":"900000000000013009"},"value":"Dairy"},{"language":"en-NZ","use":{"system":"http://snomed.info/sct","code":"900000000000013009"},"value":"Service station"},{"language":"en-NZ","use":{"system":"http://snomed.info/sct","code":"900000000000013009"},"value":"Shop"},{"language":"en-NZ","use":{"system":"http://snomed.info/sct","code":"900000000000013009"},"value":"Showhome"},{"language":"en-NZ","use":{"system":"http://snomed.info/sct","code":"900000000000013009"},"value":"Hire centre"},{"language":"en-NZ","use":{"system":"http://snomed.info/sct","code":"900000000000013009"},"value":"Laundromat"},{"language":"en-NZ","use":{"system":"http://snomed.info/sct","code":"900000000000013009"},"value":"Travel agency"},{"language":"en-NZ","use":{"system":"http://snomed.info/sct","code":"900000000000013009"},"value":"Travel agent"},{"language":"en-NZ","use":{"system":"http://snomed.info/sct","code":"900000000000013009"},"value":"Art studio"},{"language":"en-NZ","use":{"system":"http://snomed.info/sct","code":"900000000000013009"},"value":"Hairdressing salon"},{"language":"en-NZ","use":{"system":"http://snomed.info/sct","code":"900000000000013009"},"value":"Artist studio"},{"language":"en-NZ","use":{"system":"http://snomed.info/sct","code":"900000000000013009"},"value":"Bottle store"},{"language":"en-NZ","use":{"system":"http://snomed.info/sct","code":"900000000000013009"},"value":"Dance studio"},{"language":"en-NZ","use":{"system":"http://snomed.info/sct","code":"900000000000013009"},"value":"Dry cleaners shop"},{"language":"en-NZ","use":{"system":"http://snomed.info/sct","code":"900000000000013009"},"value":"Fast food outlet"},{"language":"en-NZ","use":{"system":"http://snomed.info/sct","code":"900000000000013009"},"value":"Food court"},{"language":"en-NZ","use":{"system":"http://snomed.info/sct","code":"900000000000013009"},"value":"Kiosk"},{"language":"en-NZ","use":{"system":"http://snomed.info/sct","code":"900000000000013009"},"value":"Other shops and retail buildings"},{"language":"en-NZ","use":{"system":"http://snomed.info/sct","code":"900000000000013009"},"value":"Photographer studio"},{"language":"en-NZ","use":{"system":"http://snomed.info/sct","code":"900000000000013009"},"value":"Post shop"},{"language":"en-NZ","use":{"system":"http://snomed.info/sct","code":"900000000000013009"},"value":"Real estate agent"},{"language":"en-NZ","use":{"system":"http://snomed.info/sct","code":"900000000000013009"},"value":"Retail"},{"language":"en-NZ","use":{"system":"http://snomed.info/sct","code":"900000000000013009"},"value":"Retail warehouse"},{"language":"en-NZ","use":{"system":"http://snomed.info/sct","code":"900000000000013009"},"value":"Salon"},{"language":"en-NZ","use":{"system":"http://snomed.info/sct","code":"900000000000013009"},"value":"Showroom"},{"language":"en-NZ","use":{"system":"http://snomed.info/sct","code":"900000000000013009"},"value":"Tab"},{"language":"en-NZ","use":{"system":"http://snomed.info/sct","code":"900000000000013009"},"value":"Wholesale shop"}],"property":[{"code":"parent","valueCode":"251"}]},{"code":"252","display":"Office, administration, and public transport buildings","property":[{"code":"parent","valueCode":"25"}]},{"code":"2521","display":"Office and administration buildings","designation":[{"language":"en-NZ","use":{"system":"http://snomed.info/sct","code":"900000000000013009"},"value":"Ambulance station"},{"language":"en-NZ","use":{"system":"http://snomed.info/sct","code":"900000000000013009"},"value":"Call centre"},{"language":"en-NZ","use":{"system":"http://snomed.info/sct","code":"900000000000013009"},"value":"Fire station"},{"language":"en-NZ","use":{"system":"http://snomed.info/sct","code":"900000000000013009"},"value":"Police station"},{"language":"en-NZ","use":{"system":"http://snomed.info/sct","code":"900000000000013009"},"value":"Office"},{"language":"en-NZ","use":{"system":"http://snomed.info/sct","code":"900000000000013009"},"value":"Administration"},{"language":"en-NZ","use":{"system":"http://snomed.info/sct","code":"900000000000013009"},"value":"Postal centre"},{"language":"en-NZ","use":{"system":"http://snomed.info/sct","code":"900000000000013009"},"value":"Cattery"},{"language":"en-NZ","use":{"system":"http://snomed.info/sct","code":"900000000000013009"},"value":"Veterinary clinic"},{"language":"en-NZ","use":{"system":"http://snomed.info/sct","code":"900000000000013009"},"value":"Admin"},{"language":"en-NZ","use":{"system":"http://snomed.info/sct","code":"900000000000013009"},"value":"Bank"},{"language":"en-NZ","use":{"system":"http://snomed.info/sct","code":"900000000000013009"},"value":"Civic centre"},{"language":"en-NZ","use":{"system":"http://snomed.info/sct","code":"900000000000013009"},"value":"Court house"},{"language":"en-NZ","use":{"system":"http://snomed.info/sct","code":"900000000000013009"},"value":"Courthouse"},{"language":"en-NZ","use":{"system":"http://snomed.info/sct","code":"900000000000013009"},"value":"Dog kennel"},{"language":"en-NZ","use":{"system":"http://snomed.info/sct","code":"900000000000013009"},"value":"Emergency"},{"language":"en-NZ","use":{"system":"http://snomed.info/sct","code":"900000000000013009"},"value":"Office and administration buildings"},{"language":"en-NZ","use":{"system":"http://snomed.info/sct","code":"900000000000013009"},"value":"Periodic detention centre"},{"language":"en-NZ","use":{"system":"http://snomed.info/sct","code":"900000000000013009"},"value":"SPCA  kennels"},{"language":"en-NZ","use":{"system":"http://snomed.info/sct","code":"900000000000013009"},"value":"Social service"},{"language":"en-NZ","use":{"system":"http://snomed.info/sct","code":"900000000000013009"},"value":"St john ambulance"},{"language":"en-NZ","use":{"system":"http://snomed.info/sct","code":"900000000000013009"},"value":"Surgery vet"},{"language":"en-NZ","use":{"system":"http://snomed.info/sct","code":"900000000000013009"},"value":"Vet surgery"}],"property":[{"code":"parent","valueCode":"252"}]},{"code":"2522","display":"Public transport buildings","designation":[{"language":"en-NZ","use":{"system":"http://snomed.info/sct","code":"900000000000013009"},"value":"Bus"},{"language":"en-NZ","use":{"system":"http://snomed.info/sct","code":"900000000000013009"},"value":"Bus shelter"},{"language":"en-NZ","use":{"system":"http://snomed.info/sct","code":"900000000000013009"},"value":"Airport terminal"},{"language":"en-NZ","use":{"system":"http://snomed.info/sct","code":"900000000000013009"},"value":"Bus terminal"},{"language":"en-NZ","use":{"system":"http://snomed.info/sct","code":"900000000000013009"},"value":"Ferry terminal"},{"language":"en-NZ","use":{"system":"http://snomed.info/sct","code":"900000000000013009"},"value":"Passenger transport terminal"},{"language":"en-NZ","use":{"system":"http://snomed.info/sct","code":"900000000000013009"},"value":"Rail station"}],"property":[{"code":"parent","valueCode":"252"}]},{"code":"26","display":"Factories, industrial, and storage buildings","property":[{"code":"parent","valueCode":"2"}]},{"code":"261","display":"Storage buildings","property":[{"code":"parent","valueCode":"26"}]},{"code":"2611","display":"Storage buildings","designation":[{"language":"en-NZ","use":{"system":"http://snomed.info/sct","code":"900000000000013009"},"value":"Warehouse"},{"language":"en-NZ","use":{"system":"http://snomed.info/sct","code":"900000000000013009"},"value":"Storage units"},{"language":"en-NZ","use":{"system":"http://snomed.info/sct","code":"900000000000013009"},"value":"Freight"},{"language":"en-NZ","use":{"system":"http://snomed.info/sct","code":"900000000000013009"},"value":"Storage"},{"language":"en-NZ","use":{"system":"http://snomed.info/sct","code":"900000000000013009"},"value":"Cool store"},{"language":"en-NZ","use":{"system":"http://snomed.info/sct","code":"900000000000013009"},"value":"Wool store"},{"language":"en-NZ","use":{"system":"http://snomed.info/sct","code":"900000000000013009"},"value":"Coolstore"},{"language":"en-NZ","use":{"system":"http://snomed.info/sct","code":"900000000000013009"},"value":"Road freight transport"},{"language":"en-NZ","use":{"system":"http://snomed.info/sct","code":"900000000000013009"},"value":"Parking building"},{"language":"en-NZ","use":{"system":"http://snomed.info/sct","code":"900000000000013009"},"value":"Bulk Store"},{"language":"en-NZ","use":{"system":"http://snomed.info/sct","code":"900000000000013009"},"value":"Distribution centre"},{"language":"en-NZ","use":{"system":"http://snomed.info/sct","code":"900000000000013009"},"value":"Dry store"},{"language":"en-NZ","use":{"system":"http://snomed.info/sct","code":"900000000000013009"},"value":"Lock-up"},{"language":"en-NZ","use":{"system":"http://snomed.info/sct","code":"900000000000013009"},"value":"Quarantine Building"},{"language":"en-NZ","use":{"system":"http://snomed.info/sct","code":"900000000000013009"},"value":"Storage buildings"},{"language":"en-NZ","use":{"system":"http://snomed.info/sct","code":"900000000000013009"},"value":"Transport depot"},{"language":"en-NZ","use":{"system":"http://snomed.info/sct","code":"900000000000013009"},"value":"Truck depot"},{"language":"en-NZ","use":{"system":"http://snomed.info/sct","code":"900000000000013009"},"value":"Warehouse storage"},{"language":"en-NZ","use":{"system":"http://snomed.info/sct","code":"900000000000013009"},"value":"Wharf sheds"},{"language":"en-NZ","use":{"system":"http://snomed.info/sct","code":"900000000000013009"},"value":"Woolstore"}],"property":[{"code":"parent","valueCode":"261"}]},{"code":"262","display":"Factories and industrial buildings","property":[{"code":"parent","valueCode":"26"}]},{"code":"2621","display":"Utility buildings, eg electricity, water transmission","designation":[{"language":"en-NZ","use":{"system":"http://snomed.info/sct","code":"900000000000013009"},"value":"Telephone exchange"},{"language":"en-NZ","use":{"system":"http://snomed.info/sct","code":"900000000000013009"},"value":"Drainage system"},{"language":"en-NZ","use":{"system":"http://snomed.info/sct","code":"900000000000013009"},"value":"Electricity generation facility"},{"language":"en-NZ","use":{"system":"http://snomed.info/sct","code":"900000000000013009"},"value":"Pump house"},{"language":"en-NZ","use":{"system":"http://snomed.info/sct","code":"900000000000013009"},"value":"Radio transmitter"},{"language":"en-NZ","use":{"system":"http://snomed.info/sct","code":"900000000000013009"},"value":"Sewage and Drainage System"},{"language":"en-NZ","use":{"system":"http://snomed.info/sct","code":"900000000000013009"},"value":"Sewage system"},{"language":"en-NZ","use":{"system":"http://snomed.info/sct","code":"900000000000013009"},"value":"Telecommunications antennas"},{"language":"en-NZ","use":{"system":"http://snomed.info/sct","code":"900000000000013009"},"value":"Transmitter station"},{"language":"en-NZ","use":{"system":"http://snomed.info/sct","code":"900000000000013009"},"value":"Treatment plant"},{"language":"en-NZ","use":{"system":"http://snomed.info/sct","code":"900000000000013009"},"value":"Water Storage and Supply"},{"language":"en-NZ","use":{"system":"http://snomed.info/sct","code":"900000000000013009"},"value":"Water storage"},{"language":"en-NZ","use":{"system":"http://snomed.info/sct","code":"900000000000013009"},"value":"Water tank"},{"language":"en-NZ","use":{"system":"http://snomed.info/sct","code":"900000000000013009"},"value":"Water treatment plant"},{"language":"en-NZ","use":{"system":"http://snomed.info/sct","code":"900000000000013009"},"value":"Utility buildings e.g. Electricity water transmission"}],"property":[{"code":"parent","valueCode":"262"}]},{"code":"2629","display":"Factories and other industrial buildings","designation":[{"language":"en-NZ","use":{"system":"http://snomed.info/sct","code":"900000000000013009"},"value":"Packing shed"},{"language":"en-NZ","use":{"system":"http://snomed.info/sct","code":"900000000000013009"},"value":"Bakery"},{"language":"en-NZ","use":{"system":"http://snomed.info/sct","code":"900000000000013009"},"value":"Sawmill"},{"language":"en-NZ","use":{"system":"http://snomed.info/sct","code":"900000000000013009"},"value":"Steel works"},{"language":"en-NZ","use":{"system":"http://snomed.info/sct","code":"900000000000013009"},"value":"Winery"},{"language":"en-NZ","use":{"system":"http://snomed.info/sct","code":"900000000000013009"},"value":"Newspaper printing"},{"language":"en-NZ","use":{"system":"http://snomed.info/sct","code":"900000000000013009"},"value":"Factory"},{"language":"en-NZ","use":{"system":"http://snomed.info/sct","code":"900000000000013009"},"value":"Workshop"},{"language":"en-NZ","use":{"system":"http://snomed.info/sct","code":"900000000000013009"},"value":"Foundry"},{"language":"en-NZ","use":{"system":"http://snomed.info/sct","code":"900000000000013009"},"value":"Couriers"},{"language":"en-NZ","use":{"system":"http://snomed.info/sct","code":"900000000000013009"},"value":"Industrial"},{"language":"en-NZ","use":{"system":"http://snomed.info/sct","code":"900000000000013009"},"value":"Film studio"},{"language":"en-NZ","use":{"system":"http://snomed.info/sct","code":"900000000000013009"},"value":"Abattoir"},{"language":"en-NZ","use":{"system":"http://snomed.info/sct","code":"900000000000013009"},"value":"Freezing works"},{"language":"en-NZ","use":{"system":"http://snomed.info/sct","code":"900000000000013009"},"value":"Boiler house factory"},{"language":"en-NZ","use":{"system":"http://snomed.info/sct","code":"900000000000013009"},"value":"Car wrecker"},{"language":"en-NZ","use":{"system":"http://snomed.info/sct","code":"900000000000013009"},"value":"Covered yard freezing works"},{"language":"en-NZ","use":{"system":"http://snomed.info/sct","code":"900000000000013009"},"value":"Dairy factory"},{"language":"en-NZ","use":{"system":"http://snomed.info/sct","code":"900000000000013009"},"value":"Depot"},{"language":"en-NZ","use":{"system":"http://snomed.info/sct","code":"900000000000013009"},"value":"Drying kiln sawmill"},{"language":"en-NZ","use":{"system":"http://snomed.info/sct","code":"900000000000013009"},"value":"Factories and industrial buildings"},{"language":"en-NZ","use":{"system":"http://snomed.info/sct","code":"900000000000013009"},"value":"Fertilizer works"},{"language":"en-NZ","use":{"system":"http://snomed.info/sct","code":"900000000000013009"},"value":"Film post production"},{"language":"en-NZ","use":{"system":"http://snomed.info/sct","code":"900000000000013009"},"value":"Hanger"},{"language":"en-NZ","use":{"system":"http://snomed.info/sct","code":"900000000000013009"},"value":"Home kill processing plant"},{"language":"en-NZ","use":{"system":"http://snomed.info/sct","code":"900000000000013009"},"value":"Industrial building"},{"language":"en-NZ","use":{"system":"http://snomed.info/sct","code":"900000000000013009"},"value":"Joinery shop"},{"language":"en-NZ","use":{"system":"http://snomed.info/sct","code":"900000000000013009"},"value":"Laundry dry cleaners"},{"language":"en-NZ","use":{"system":"http://snomed.info/sct","code":"900000000000013009"},"value":"Lighthouse"},{"language":"en-NZ","use":{"system":"http://snomed.info/sct","code":"900000000000013009"},"value":"Optic network utility"},{"language":"en-NZ","use":{"system":"http://snomed.info/sct","code":"900000000000013009"},"value":"Packaging shed"},{"language":"en-NZ","use":{"system":"http://snomed.info/sct","code":"900000000000013009"},"value":"Portacom"},{"language":"en-NZ","use":{"system":"http://snomed.info/sct","code":"900000000000013009"},"value":"Printer bindery"},{"language":"en-NZ","use":{"system":"http://snomed.info/sct","code":"900000000000013009"},"value":"Radio studio"},{"language":"en-NZ","use":{"system":"http://snomed.info/sct","code":"900000000000013009"},"value":"Recording"},{"language":"en-NZ","use":{"system":"http://snomed.info/sct","code":"900000000000013009"},"value":"Recycle transfer station"},{"language":"en-NZ","use":{"system":"http://snomed.info/sct","code":"900000000000013009"},"value":"Research laboratory"},{"language":"en-NZ","use":{"system":"http://snomed.info/sct","code":"900000000000013009"},"value":"Spray painters"},{"language":"en-NZ","use":{"system":"http://snomed.info/sct","code":"900000000000013009"},"value":"Sub station"},{"language":"en-NZ","use":{"system":"http://snomed.info/sct","code":"900000000000013009"},"value":"Timber yards sawmill"},{"language":"en-NZ","use":{"system":"http://snomed.info/sct","code":"900000000000013009"},"value":"Transfer station"},{"language":"en-NZ","use":{"system":"http://snomed.info/sct","code":"900000000000013009"},"value":"Unit transformer project"},{"language":"en-NZ","use":{"system":"http://snomed.info/sct","code":"900000000000013009"},"value":"Vehicle testing station"},{"language":"en-NZ","use":{"system":"http://snomed.info/sct","code":"900000000000013009"},"value":"Water purification plant"},{"language":"en-NZ","use":{"system":"http://snomed.info/sct","code":"900000000000013009"},"value":"Workshop industrial"}],"property":[{"code":"parent","valueCode":"262"}]},{"code":"27","display":"Farm buildings","property":[{"code":"parent","valueCode":"2"}]},{"code":"271","display":"Farm buildings","property":[{"code":"parent","valueCode":"27"}]},{"code":"2711","display":"Farm buildings","designation":[{"language":"en-NZ","use":{"system":"http://snomed.info/sct","code":"900000000000013009"},"value":"Farm"},{"language":"en-NZ","use":{"system":"http://snomed.info/sct","code":"900000000000013009"},"value":"Nursery"},{"language":"en-NZ","use":{"system":"http://snomed.info/sct","code":"900000000000013009"},"value":"Hay barn"},{"language":"en-NZ","use":{"system":"http://snomed.info/sct","code":"900000000000013009"},"value":"Implement shed"},{"language":"en-NZ","use":{"system":"http://snomed.info/sct","code":"900000000000013009"},"value":"Milking shed"},{"language":"en-NZ","use":{"system":"http://snomed.info/sct","code":"900000000000013009"},"value":"Apiary"},{"language":"en-NZ","use":{"system":"http://snomed.info/sct","code":"900000000000013009"},"value":"Piggery"},{"language":"en-NZ","use":{"system":"http://snomed.info/sct","code":"900000000000013009"},"value":"Woolshed"},{"language":"en-NZ","use":{"system":"http://snomed.info/sct","code":"900000000000013009"},"value":"Coolstore farm"},{"language":"en-NZ","use":{"system":"http://snomed.info/sct","code":"900000000000013009"},"value":"Covered yard"},{"language":"en-NZ","use":{"system":"http://snomed.info/sct","code":"900000000000013009"},"value":"Drying kiln farm"},{"language":"en-NZ","use":{"system":"http://snomed.info/sct","code":"900000000000013009"},"value":"Farm buildings"},{"language":"en-NZ","use":{"system":"http://snomed.info/sct","code":"900000000000013009"},"value":"Fattening unit"},{"language":"en-NZ","use":{"system":"http://snomed.info/sct","code":"900000000000013009"},"value":"Glass house commerical"},{"language":"en-NZ","use":{"system":"http://snomed.info/sct","code":"900000000000013009"},"value":"Glasshouse"},{"language":"en-NZ","use":{"system":"http://snomed.info/sct","code":"900000000000013009"},"value":"Haybarn"},{"language":"en-NZ","use":{"system":"http://snomed.info/sct","code":"900000000000013009"},"value":"Hen house commerical"},{"language":"en-NZ","use":{"system":"http://snomed.info/sct","code":"900000000000013009"},"value":"Plastic house"},{"language":"en-NZ","use":{"system":"http://snomed.info/sct","code":"900000000000013009"},"value":"Shade house"},{"language":"en-NZ","use":{"system":"http://snomed.info/sct","code":"900000000000013009"},"value":"Shearing shed"},{"language":"en-NZ","use":{"system":"http://snomed.info/sct","code":"900000000000013009"},"value":"Stable farm"},{"language":"en-NZ","use":{"system":"http://snomed.info/sct","code":"900000000000013009"},"value":"Tunnel"},{"language":"en-NZ","use":{"system":"http://snomed.info/sct","code":"900000000000013009"},"value":"Tunnel house"},{"language":"en-NZ","use":{"system":"http://snomed.info/sct","code":"900000000000013009"},"value":"Wool shed"}],"property":[{"code":"parent","valueCode":"271"}]},{"code":"3","display":"Non-building construction"},{"code":"31","display":"Non-building construction","property":[{"code":"parent","valueCode":"3"}]},{"code":"311","display":"Non-building construction","property":[{"code":"parent","valueCode":"31"}]},{"code":"3111","display":"Non-building construction","property":[{"code":"parent","valueCode":"311"}]}]}