{"resourceType":"ValueSet","id":"canshare-sact-er-expression","meta":{"versionId":"1","lastUpdated":"2024-07-25T17:28:39.569+12:00"},"language":"en-x-sctlang-23162100-0210105","url":"https://nzhts.digital.health.nz/fhir/ValueSet/canshare-sact-er-expression","identifier":[{"system":"http://canshare.co.nz/fhir/NamingSystem/valuesets","value":"canshare-sact-er-expression"}],"version":"20240318","name":"canshare-sact-er-expression","title":"NZ SACT ER expression","status":"active","experimental":false,"publisher":"Te Aho o Te Kahu","contact":[{"telecom":[{"system":"email","value":"info@teaho.govt.nz"}]}],"description":"A diagnosis of whether or not a tumour is estrogen receptive (ER) minus inconculsive value.","compose":{"include":[{"system":"http://snomed.info/sct","version":"http://snomed.info/sct/21000210109","filter":[{"property":"constraint","op":"=","value":"^ 253331000210104 |New Zealand cancer ER expression reference set| MINUS 419984006 |Inconclusive (qualifier value)|  "}]}]}}