{"resourceType":"ValueSet","id":"canshare-tnm-haematology-mf-or-ss-pt","meta":{"versionId":"1","lastUpdated":"2024-07-25T17:30:45.325+12:00"},"language":"en-x-sctlang-23162100-0210105","url":"https://nzhts.digital.health.nz/fhir/ValueSet/canshare-tnm-haematology-mf-or-ss-pt","identifier":[{"system":"http://canshare.co.nz/fhir/NamingSystem/valuesets","value":"canshare-tnm-haematology-mf-or-ss-pt"}],"version":"20240318","name":"canshare-tnm-haematology-mf-or-ss-pt","title":"NZ AJCC haematology mycosis fungoides or sezary syndrome pathological T category","status":"active","experimental":false,"publisher":"Te Aho o Te Kahu","contact":[{"telecom":[{"system":"email","value":"info@teaho.govt.nz"}]}],"description":"A pathological tumour stage (pT) of a mycosis fungoides or sezary syndrome cutaneous lymphoma, using the AJCC cancer staging manual (latest edition).","compose":{"include":[{"system":"http://snomed.info/sct","version":"http://snomed.info/sct/21000210109","filter":[{"property":"constraint","op":"=","value":"^253591000210107 |New Zealand AJCC 8th edition haematology mycosis fungoides OR sezary syndrome pathological T category reference set|"}]}]}}