{
  "resourceType": "ValueSet",
  "meta": {
    "versionId": "1",
    "lastUpdated": "2024-10-29T17:15:14.721+13:00",
    "profile": [
      "http://hl7.org/fhir/StructureDefinition/shareablevalueset"
    ]
  },
  "url": "http://hl7.org/fhir/uv/ips/ValueSet/pregnancies-summary-uv-ips",
  "identifier": [
    {
      "use": "official",
      "system": "http://art-decor.org/ns/oids/vs",
      "value": "2.16.840.1.113883.11.22.21"
    }
  ],
  "version": "1.1.0",
  "name": "PregnanciesSummaryUvIps",
  "title": "Pregnancies Summary - IPS",
  "status": "active",
  "experimental": false,
  "copyright": "This material contains content from LOINC (http://loinc.org). LOINC is copyright © 1995-2020, Regenstrief Institute, Inc. and the Logical Observation Identifiers Names and Codes (LOINC) Committee and is available at no cost under the license at http://loinc.org/license. LOINC® is a registered United States trademark of Regenstrief Institute, Inc",
  "expansion": {
    "identifier": "be47f574-eb4d-4ea2-bf1e-e5a14cdd529c",
    "timestamp": "2024-11-01T20:25:27+13:00",
    "total": 9,
    "offset": 0,
    "parameter": [
      {
        "name": "version",
        "valueUri": "http://loinc.org|2.78"
      },
      {
        "name": "count",
        "valueInteger": 100
      },
      {
        "name": "offset",
        "valueInteger": 0
      }
    ],
    "contains": [
      {
        "system": "http://loinc.org",
        "code": "11636-8",
        "display": "[#] Births.live"
      },
      {
        "system": "http://loinc.org",
        "code": "11637-6",
        "display": "[#] Births.preterm"
      },
      {
        "system": "http://loinc.org",
        "code": "11638-4",
        "display": "[#] Births.still living"
      },
      {
        "system": "http://loinc.org",
        "code": "11639-2",
        "display": "[#] Births.term"
      },
      {
        "system": "http://loinc.org",
        "code": "11640-0",
        "display": "[#] Births total"
      },
      {
        "system": "http://loinc.org",
        "code": "11612-9",
        "display": "[#] Abortions"
      },
      {
        "system": "http://loinc.org",
        "code": "11613-7",
        "display": "[#] Abortions.induced"
      },
      {
        "system": "http://loinc.org",
        "code": "11614-5",
        "display": "[#] Abortions.spontaneous"
      },
      {
        "system": "http://loinc.org",
        "code": "33065-4",
        "display": "[#] Ectopic pregnancy"
      }
    ]
  },
  "id": "pregnancies-summary-uv-ips"
}
